RobotStackTracer/__init__.py
robotframework_stacktrace-0.4.1.dist-info/LICENSE
robotframework_stacktrace-0.4.1.dist-info/METADATA
robotframework_stacktrace-0.4.1.dist-info/WHEEL
robotframework_stacktrace-0.4.1.dist-info/top_level.txt
robotframework_stacktrace-0.4.1.dist-info/RECORD
