Metadata-Version: 2.1
Name: robotframework-stacktrace
Version: 0.4.1
Summary: A listener that prints a Stack Trace to console to faster find the code section where the failure appears.
Home-page: https://github.com/MarketSquare/robotframework-stacktrace
Author: René Rohner(Snooz82)
Author-email: snooz@posteo.de
License: UNKNOWN
Platform: UNKNOWN
Classifier: Programming Language :: Python :: 3
Classifier: Programming Language :: Python :: 3.6
Classifier: Programming Language :: Python :: 3.7
Classifier: License :: OSI Approved :: Apache Software License
Classifier: Operating System :: OS Independent
Classifier: Topic :: Software Development :: Testing
Classifier: Topic :: Software Development :: Testing :: Acceptance
Classifier: Framework :: Robot Framework
Requires-Python: >=3.6
